setup.cfg
setup.py
python_zeppelin.egg-info/PKG-INFO
python_zeppelin.egg-info/SOURCES.txt
python_zeppelin.egg-info/dependency_links.txt
python_zeppelin.egg-info/entry_points.txt
python_zeppelin.egg-info/requires.txt
python_zeppelin.egg-info/top_level.txt
tests/__init__.py
tests/test_legacy_converter.py
tests/test_new_converter.py
zeppelin/__init__.py
zeppelin/legacy.py
zeppelin/cli/__init__.py
zeppelin/cli/convert.py
zeppelin/cli/execute.py
zeppelin/converters/__init__.py
zeppelin/converters/markdown.py
zeppelin/executors/__init__.py
zeppelin/executors/notebook_executor.py